{
    "ranked_movies": [
        {
            "rank": 1,
            "title": "About Time",
            "reason": "Explicitly mentioned as a bittersweet movie that deeply impacted a user, sparking a realization about the preciousness of time and family relationships."
        },
        {
            "rank": 2,
            "title": "I Saw the Devil",
            "reason": "Given as the prime example in a post asking for movies that get progressively more depressing and messed up, with a bleak ending."
        },
        {
            "rank": 3,
            "title": "Requiem for a Dream",
            "reason": "Top-voted comment in the 'depressing movies' thread, described as the best movie you'll only want to watch once due to its intensity."
        },
        {
            "rank": 4,
            "title": "Grave of the Fireflies",
            "reason": "Highly discussed as an extremely depressing movie that offers no happiness and leaves viewers destroyed."
        },
        {
            "rank": 5,
            "title": "Oldboy",
            "reason": "Frequently recommended in the same thread as 'I Saw the Devil' and 'Requiem for a Dream' for its dark and twisted narrative."
        },
        {
            "rank": 6,
            "title": "Come and See",
            "reason": "Specifically called out with its year (1985) as a quintessential and harrowing depressing war film."
        },
        {
            "rank": 7,
            "title": "The Road",
            "reason": "Recommended for its consistently downward trajectory and ambiguous, but likely bleak, ending."
        },
        {
            "rank": 8,
            "title": "Parasite",
            "reason": "Listed among the top depressing movies for its social commentary and tragic turns."
        },
        {
            "rank": 9,
            "title": "Manchester by the Sea",
            "reason": "Mentioned with a simple 'Oof', indicating its recognition as a profoundly sad film about grief."
        },
        {
            "rank": 10,
            "title": "Leaving Las Vegas",
            "reason": "Recommended in the list of progressively depressing films."
        },
        {
            "rank": 11,
            "title": "Eden Lake",
            "reason": "Included in the list of movies that are dark and messed up."
        },
        {
            "rank": 12,
            "title": "Children of Men",
            "reason": "Suggested as a movie that fits the theme of being dark and depressing."
        },
        {
            "rank": 13,
            "title": "Thirteen",
            "reason": "Mentioned as a film that is particularly shocking and depressing, especially upon realizing the characters' ages."
        },
        {
            "rank": 14,
            "title": "Dancer in the Dark",
            "reason": "Listed alongside Parasite as a famously bleak and tragic movie."
        },
        {
            "rank": 15,
            "title": "Mary and Max",
            "reason": "The central example in a post about unexpectedly dark movies; described as layering one bummer on top of another."
        },
        {
            "rank": 16,
            "title": "Friendship",
            "reason": "The other central example in the same post, noted for its tragic core of loneliness and failure to connect despite being a comedy."
        },
        {
            "rank": 17,
            "title": "Groundhog Day",
            "reason": "The subject of a 'Bad Movie Description' post that labeled it a 'depressing movie about adulthood,' highlighting its deeper, relatable themes within a comedy."
        },
        {
            "rank": 18,
            "title": "Soul",
            "reason": "Discussed as the last 'genuinely great' Pixar film that deals with deep, existential themes of life's purpose."
        },
        {
            "rank": 19,
            "title": "The Brave Little Toaster",
            "reason": "Cited as a movie that unexpectedly traumatized a generation of children who assumed it was a normal kids' film."
        },
        {
            "rank": 20,
            "title": "Wall Street",
            "reason": "Discussed in a historical context where its anti-capitalist message backfired, instead making audiences admire the luxury and excess it portrayed."
        }
    ]
}